vplanet/__init__.py
vplanet/custom_units.py
vplanet/log.py
vplanet/logger.py
vplanet/output.py
vplanet/quantity.py
vplanet/quantity_support.py
vplanet/vplanet_core.cpython-36m-darwin.so
vplanet/vplanet_help.py
vplanet/wrapper.py
vplanet-2.5.26.data/data/VERSION
vplanet-2.5.26.dist-info/LICENSE
vplanet-2.5.26.dist-info/METADATA
vplanet-2.5.26.dist-info/WHEEL
vplanet-2.5.26.dist-info/entry_points.txt
vplanet-2.5.26.dist-info/top_level.txt
vplanet-2.5.26.dist-info/RECORD
