Metadata-Version: 2.1
Name: vplanet
Version: 2.5.26
Summary: The virtual planet simulator
Home-page: https://github.com/VirtualPlanetaryLaboratory/vplanet
Author: Rory Barnes
Author-email: rkb9@uw.edu
License: MIT
Platform: UNKNOWN
Requires-Python: >=3.6
License-File: LICENSE
Requires-Dist: vplot (>=1.0.5)
Requires-Dist: vspace (>=2.3.2)
Requires-Dist: bigplanet (>=3.0.1)
Requires-Dist: multiplanet (>=2.0.3)
Requires-Dist: astropy (>=3.0)
Requires-Dist: numpy
Requires-Dist: tqdm
Requires-Dist: seaborn
